{
  "settings": {
    "profanity_filter": true,
    "volume_db": -5.0,
    "pause_ms": 1000,
    "intro": "intro.mp3",
    "outro": "outro.mp3",
    "music_volume_db": -6.0
  },
  "Jamie": {
    "description": "Energetic, upbeat host — quick jokes, enthusiastic transitions, drives the conversation with high energy.",
    "voice": "5cad89c9-d88a-4832-89fb-55f2f16d13d3",
    "volume_db": 0.0,
    "pause_ms": 120
  },
  "Carol": {
    "description": "Dry-witted co-host — concise, skeptical, asks sharp follow-ups and teases Alex with sardonic humor.",
    "voice": "f9836c6e-a0bd-460e-9d3c-f7299fa60f94",
    "volume_db": -2.0,
    "pause_ms": 180
  }
}